kg_prometheusstack/__init__.py
kg_prometheusstack/builder.py
kg_prometheusstack/option.py
kg_prometheusstack/py.typed
kg_prometheusstack/tests/__init__.py
kg_prometheusstack/tests/test_builder.py
kg_prometheusstack-0.8.3.dist-info/LICENSE
kg_prometheusstack-0.8.3.dist-info/METADATA
kg_prometheusstack-0.8.3.dist-info/WHEEL
kg_prometheusstack-0.8.3.dist-info/top_level.txt
kg_prometheusstack-0.8.3.dist-info/RECORD
