Metadata-Version: 2.1
Name: kg-prometheusstack
Version: 0.8.3
Summary: KubraGen Builder: Prometheus Stack
Home-page: https://github.com/RangelReale/kg_prometheusstack
Author: Rangel Reale
Author-email: rangelreale@gmail.com
License: UNKNOWN
Platform: UNKNOWN
Classifier: Programming Language :: Python :: 3
Classifier: License :: OSI Approved :: MIT License
Classifier: Operating System :: OS Independent
Requires-Python: >=3.6
Requires-Dist: kubragen (>=0.8.4)
Requires-Dist: kg-prometheus (>=0.8.1)
Requires-Dist: kg-nodeexporter (>=0.8.0)
Requires-Dist: kg-kubestatemetrics (>=0.8.0)
Requires-Dist: kg-grafana (>=0.8.3)
